README.md
setup.cfg
setup.py
parabam/__init__.py
parabam/chaser.c
parabam/core.c
parabam/merger.c
parabam.egg-info/PKG-INFO
parabam.egg-info/SOURCES.txt
parabam.egg-info/dependency_links.txt
parabam.egg-info/requires.txt
parabam.egg-info/top_level.txt
parabam/bin/parabam
parabam/command/__init__.py
parabam/command/core.c
parabam/command/stat.c
parabam/command/subset.c