Metadata-Version: 1.0
Name: parabam
Version: 3.0.1
Summary: Parallel BAM File Analysis
Home-page: https://github.com/cancerit/parabam
Author: JHR Farmery
Author-email: cgphelp@sanger.ac.uk
License: GPL
Platform: UNKNOWN
